spatio-0.1.8.dist-info/METADATA
spatio-0.1.8.dist-info/WHEEL
spatio-0.1.8.dist-info/licenses/LICENSE
spatio/__init__.py
spatio/_spatio.cpython-312-darwin.so
spatio/types.py
spatio-0.1.8.dist-info/RECORD
