Metadata-Version: 2.4
Name: spatio
Version: 0.1.8
Requires-Dist: pytest>=7.0.0 ; extra == 'dev'
Requires-Dist: pytest-benchmark>=4.0.0 ; extra == 'dev'
Requires-Dist: pytest-cov>=4.0.0 ; extra == 'dev'
Requires-Dist: pytest-xdist>=3.0.0 ; extra == 'dev'
Requires-Dist: bandit>=1.8.6 ; extra == 'dev'
Provides-Extra: dev
License-File: LICENSE
Summary: Blazingly fast spatio-temporal database library
Author-email: Petro Kvartsianyi <pkvartsianyi@example.com>
Requires-Python: >=3.9
Project-URL: Homepage, https://github.com/pkvartsianyi/spatio
Project-URL: Documentation, https://github.com/pkvartsianyi/spatio#readme
Project-URL: Repository, https://github.com/pkvartsianyi/spatio
Project-URL: PyPI, https://pypi.org/project/spatio
Project-URL: Crates.io, https://crates.io/crates/spatio
Project-URL: Changelog, https://github.com/pkvartsianyi/spatio/releases
Project-URL: Issues, https://github.com/pkvartsianyi/spatio/issues
